Metadata-Version: 1.0
Name: containers
Version: 0.0.4
Summary: automatic typed collections in python using decorators
Home-page: https://github.com/abe-winter/containers
Author: Abe Winter
Author-email: awinter.public@gmail.com
License: MIT
Platform: UNKNOWN
